{"is_source_file": true, "format": "Dart", "description": "This source file is a Flutter application entry point that sets up a simple UI with a title and a centered progress indicator.", "external_files": ["package:flutter/material.dart"], "external_methods": ["runApp", "MaterialApp", "ThemeData", "ColorScheme.fromSeed", "Scaffold", "AppBar", "Theme.of", "Center", "Column", "Text", "SizedBox", "CircularProgressIndicator"], "published": ["main"], "classes": [{"name": "MyApp", "description": "A StatelessWidget that sets up the MaterialApp with theme and home page."}, {"name": "MyHomePage", "description": "A StatefulWidget representing the main page with a title."}, {"name": "_MyHomePageState", "description": "State class managing the UI of MyHomePage, building the Scaffold with an AppBar and centered content."}], "methods": [{"name": "main", "description": "The entry point of the application, initializing and running MyApp."}, {"name": "build", "description": "Build method of MyApp, creating the MaterialApp widget."}, {"name": "build", "description": "Build method of _MyHomePageState, creating the Scaffold with UI components."}], "calls": ["runApp", "MaterialApp", "ThemeData", "ColorScheme.fromSeed", "Scaffold", "AppBar", "Theme.of", "Center", "Column", "Text", "SizedBox", "CircularProgressIndicator"], "search-terms": ["Flutter", "MaterialApp", "main.dart", "MyApp", "MyHomePage", "StatefulWidget", "StatelessWidget", "ProgressIndicator", "UI", "frontend"], "state": 2, "file_id": 17, "knowledge_revision": 37, "git_revision": "", "hash": "82991bd2980248655cb49d31dad30964", "format-version": 4, "code-base-name": "book_app_frontend", "filename": "book_app_frontend/lib/main.dart", "revision_history": [{"37": ""}]}